[{"name": "geometry.hyperbolic.time_HyperbolicPlane_polygon", "idx": 0, "pretty_name": "geometry.hyperbolic.time_HyperbolicPlane_polygon({{(x^2 + y^2) - 1 \u2264 0}})", "last_rev": 2319, "last_value": 0.00044037387500021435, "last_err": 6.942461358660263e-06, "prev_value": null, "change_rev": null}, {"name": "geometry.hyperbolic.time_HyperbolicPlane_polygon", "idx": 1, "pretty_name": "geometry.hyperbolic.time_HyperbolicPlane_polygon([{(x^2 + y^2) - 30*x + 224 \u2264 0}, \u2026 31 more])", "last_rev": 2319, "last_value": 0.03498031649996847, "last_err": 0.0, "prev_value": 0.03441390700000113, "change_rev": [2222, 2319]}, {"name": "geometry.hyperbolic.time_HyperbolicPlane_polygon", "idx": 2, "pretty_name": "geometry.hyperbolic.time_HyperbolicPlane_polygon([{(x^2 + y^2) - 1932*x + 933155 \u2264 0}, \u2026 1023 more])", "last_rev": 2319, "last_value": 0.8265580354999997, "last_err": 0.0, "prev_value": null, "change_rev": null}, {"name": "geometry.hyperbolic.time_HyperbolicPlane_polygon", "idx": 3, "pretty_name": "geometry.hyperbolic.time_HyperbolicPlane_polygon([{(x^2 + y^2) - 3198*x + 2556800 \u2264 0}, \u2026 2047 more])", "last_rev": 2319, "last_value": 2.3114048224999806, "last_err": 0.0, "prev_value": null, "change_rev": null}, {"name": "geometry.hyperbolic.time_HyperbolicPlane_polygon", "idx": 4, "pretty_name": "geometry.hyperbolic.time_HyperbolicPlane_polygon([{(x^2 + y^2) - 4898*x + 5997600 \u2264 0}, \u2026 4095 more])", "last_rev": 2319, "last_value": 2.4637600459999476, "last_err": 0.0, "prev_value": null, "change_rev": null}, {"name": "polygons.time_triangle", "idx": 0, "pretty_name": "polygons.time_triangle({3, 4, 5})", "last_rev": 2319, "last_value": 0.0006904534999705447, "last_err": 5.8963036162194845e-05, "prev_value": null, "change_rev": null}, {"name": "polygons.time_triangle", "idx": 1, "pretty_name": "polygons.time_triangle({24, 22, 23})", "last_rev": 2319, "last_value": 0.0015234199999838438, "last_err": 0.00011721879915690037, "prev_value": null, "change_rev": null}, {"name": "polygons.time_triangle", "idx": 2, "pretty_name": "polygons.time_triangle({24, 25, 23})", "last_rev": 2319, "last_value": 0.0008981594999966092, "last_err": 6.357843360359868e-05, "prev_value": null, "change_rev": null}, {"name": "polygons.time_triangle", "idx": 3, "pretty_name": "polygons.time_triangle({24, 25, 26})", "last_rev": 2319, "last_value": 0.0015898240000069563, "last_err": 0.00011291927540061545, "prev_value": null, "change_rev": null}, {"name": "polygons.time_triangle", "idx": 4, "pretty_name": "polygons.time_triangle({48, 26, 75})", "last_rev": 2319, "last_value": 0.048297394499996926, "last_err": 0.0019290028253439175, "prev_value": null, "change_rev": null}]